phenology/__init__.py
phenology/fit/__init__.py
phenology/fit/func_pheno.py
phenology/gsc/__init__.py
phenology/gsc/gsc.py
phenology/opl/__init__.py
phenology/opl/func_opl.py
phenology/opl/v1/__init__.py
phenology/opl/v1/api_opl_v1.cp313-win_amd64.pyd
phenology/opl/v1/func_opl.py
phenology/plot/__init__.py
phenology/utils/__init__.py
phenology/utils/func_common.py
phenology/utils/func_numpy/__init__.py
phenology/utils/func_numpy/api_resample.cp313-win_amd64.pyd
phenology/utils/func_xarray/__init__.py
phenology-0.0.27.dist-info/LICENSE
phenology-0.0.27.dist-info/METADATA
phenology-0.0.27.dist-info/WHEEL
phenology-0.0.27.dist-info/top_level.txt
phenology-0.0.27.dist-info/RECORD
