Metadata-Version: 2.1
Name: phenology
Version: 0.0.27
Summary: A small package for phenology analysis
Home-page: https://github.com/spjace/phenology
Author: Shen Pengju
Author-email: spjace@sina.com
Classifier: Programming Language :: Python :: 3
Classifier: License :: OSI Approved :: MIT License
Classifier: Operating System :: OS Independent
Requires-Python: >=3.7
License-File: LICENSE
Requires-Dist: geopandas
Requires-Dist: joblib
Requires-Dist: matplotlib
Requires-Dist: numpy
Requires-Dist: pandas
Requires-Dist: pyproj
Requires-Dist: scikit-learn
Requires-Dist: scipy
Requires-Dist: Shapely
Requires-Dist: statsmodels
Requires-Dist: tqdm
Requires-Dist: xarray
